gdmix/__init__.py
gdmix/gdmix.py
gdmix/params.py
gdmix/drivers/__init__.py
gdmix/drivers/driver.py
gdmix/drivers/fixed_effect_driver.py
gdmix/drivers/random_effect_driver.py
gdmix/factory/__init__.py
gdmix/factory/driver_factory.py
gdmix/factory/model_factory.py
gdmix/io/__init__.py
gdmix/io/dataset_metadata.py
gdmix/io/input_data_pipeline.py
gdmix/models/__init__.py
gdmix/models/api.py
gdmix/models/detext_writer.py
gdmix/models/schemas.py
gdmix/models/custom/__init__.py
gdmix/models/custom/base_lr_params.py
gdmix/models/custom/binary_logistic_regression.py
gdmix/models/custom/fixed_effect_lr_lbfgs_model.py
gdmix/models/custom/random_effect_lr_lbfgs_model.py
gdmix/models/custom/scipy/__init__.py
gdmix/models/custom/scipy/job_consumers.py
gdmix/models/estimator/__init__.py
gdmix/models/estimator/fixed_effect_detext_estimator_model.py
gdmix/util/__init__.py
gdmix/util/constants.py
gdmix/util/distribution_utils.py
gdmix/util/io_utils.py
gdmix_trainer-0.3.0.dist-info/METADATA
gdmix_trainer-0.3.0.dist-info/WHEEL
gdmix_trainer-0.3.0.dist-info/top_level.txt
gdmix_trainer-0.3.0.dist-info/RECORD
