Metadata-Version: 2.1
Name: gdmix-trainer
Version: 0.3.0
Summary: UNKNOWN
Home-page: UNKNOWN
License: BSD-2-CLAUSE
Platform: UNKNOWN
Classifier: Programming Language :: Python :: 3.7
Classifier: Intended Audience :: Science/Research
Classifier: Intended Audience :: Developers
Classifier: License :: OSI Approved
Requires-Python: >=3.7
Requires-Dist: setuptools (>=41.0.0)
Requires-Dist: tensorflow (==1.15.2)
Requires-Dist: tensorflow-ranking (==0.1.4)
Requires-Dist: fastavro (==0.21.22)
Requires-Dist: decorator (==4.4.2)
Requires-Dist: detext-nodep (==2.0.9)
Requires-Dist: psutil (==5.7.0)
Requires-Dist: scipy (==1.3.2)
Requires-Dist: scikit-learn (==0.21.2)
Requires-Dist: smart-arg (==0.2.12)
